mediumdb
