Metadata-Version: 2.1
Name: mediumdb
Version: 0.0.4
Summary: Medium driver.
Home-page: https://github.com/sujitech/medium_driver
Author: Mindey
Author-email: mindey@qq.com
License: ASK FOR PERMISSIONS
Platform: UNKNOWN
Provides-Extra: test
